{
  "schemaVersion": 1,
  "subject": "english",
  "course": "our-world",
  "level": 4,
  "unit": 9,
  "unitTitle": "The Science of Fun",
  "source": {
    "type": "lesson-planner-scan",
    "file": "planner.pdf",
    "verified": true,
    "note": "Unit 9 vocabulary scanned from the full Level 4 planner.pdf (pages 290-319, pdf_offset 289): Vocabulary 1/2, Academic Language and Content Vocabulary from Grammar 1/2 and Reading, and Related Vocabulary from the Vocab 1, Song, and Reading 'Be the Expert' sidebars. Mission and Project pages had no Content Vocabulary line this unit; the Reader's word list duplicated Vocabulary 1 words already covered."
  },
  "wordIds": [
    "global_force",
    "global_happen",
    "global_push",
    "global_pull",
    "global_swing_toy",
    "global_skater",
    "global_forward",
    "global_backward",
    "global_spin",
    "global_fall_over",
    "global_balance",
    "global_down",
    "global_connect",
    "global_rub",
    "global_friction",
    "global_athlete",
    "global_jump",
    "global_skier",
    "global_away_from",
    "global_direction",
    "global_toward",
    "global_lean",
    "global_gravity",
    "global_merry_go_round",
    "global_seesaw",
    "global_skateboarder",
    "global_tetherball",
    "global_safety_bar",
    "global_steep",
    "global_centripetal_force",
    "global_inertia",
    "global_experience",
    "global_figure_skating",
    "global_freestyle_skiing",
    "global_ice_rink",
    "global_twist",
    "global_gyroscope",
    "global_independently",
    "global_motion_sickness",
    "global_structure",
    "global_motion",
    "global_theme_park",
    "global_describe",
    "global_match",
    "global_definitions",
    "global_instructions",
    "global_description"
  ],
  "vocab1WordIds": [
    "global_force",
    "global_happen",
    "global_push",
    "global_pull",
    "global_swing_toy",
    "global_skater",
    "global_forward",
    "global_backward",
    "global_spin",
    "global_fall_over",
    "global_balance",
    "global_down",
    "global_connect",
    "global_rub",
    "global_friction"
  ],
  "vocab2WordIds": [
    "global_away_from",
    "global_direction",
    "global_toward",
    "global_lean",
    "global_gravity"
  ],
  "academicWordIds": [
    "global_describe",
    "global_match",
    "global_definitions",
    "global_instructions",
    "global_description"
  ],
  "contentWordIds": [
    "global_athlete",
    "global_jump",
    "global_skier",
    "global_merry_go_round",
    "global_seesaw",
    "global_skateboarder",
    "global_tetherball",
    "global_safety_bar",
    "global_steep",
    "global_centripetal_force",
    "global_inertia",
    "global_experience"
  ],
  "relatedWordIds": [
    "global_figure_skating",
    "global_freestyle_skiing",
    "global_ice_rink",
    "global_twist",
    "global_gyroscope",
    "global_independently",
    "global_motion_sickness",
    "global_structure",
    "global_motion",
    "global_theme_park"
  ],
  "words": [
    {
      "id": "global_force",
      "type": "vocabulary",
      "word": "a force",
      "normalizedWord": "force",
      "displayEmoji": "💪⚡",
      "emojiDescription": "strong arm with a lightning bolt for push/pull energy",
      "partOfSpeech": "noun",
      "syllables": "force",
      "ipa": "fɔːrs",
      "meaning": "a push or a pull that can move something",
      "example": "You need force to push or pull something.",
      "exampleJp": "何かを押したり引いたりするには力が必要です。",
      "japanese": {
        "word": "力（ちから）",
        "reading": "ちから",
        "meaning": "物を動かすための押す力や引く力。",
        "needsReview": true
      },
      "sources": [
        {
          "subject": "english",
          "course": "our-world",
          "level": 4,
          "unit": 9,
          "component": "vocab-1",
          "tag": "OW4-U9-V1",
          "lessonStatus": "draft",
          "lessonId": "ow-l4-u9-vocab-1"
        }
      ],
      "tags": [
        "vocabulary",
        "target",
        "vocab-1",
        "force-and-motion",
        "OW4-U9-V1"
      ],
      "additionalExamples": [
        "The more force you use, the faster the ball moves."
      ],
      "additionalExamplesJp": [
        "力を強く使うほど、ボールは速く動きます。"
      ]
    },
    {
      "id": "global_happen",
      "type": "vocabulary",
      "word": "happen",
      "normalizedWord": "happen",
      "displayEmoji": "❓➡️",
      "emojiDescription": "question mark turning into an arrow showing an event occurring",
      "partOfSpeech": "verb",
      "syllables": "hap-pen",
      "ipa": "ˈhæpən",
      "meaning": "to take place; to occur",
      "example": "Force happens when we push or pull.",
      "exampleJp": "私たちが押したり引いたりすると、力が生まれます。",
      "japanese": {
        "word": "起こる",
        "reading": "おこる",
        "meaning": "何かが実際に生じること。",
        "needsReview": true
      },
      "sources": [
        {
          "subject": "english",
          "course": "our-world",
          "level": 4,
          "unit": 9,
          "component": "vocab-1",
          "tag": "OW4-U9-V1",
          "lessonStatus": "draft",
          "lessonId": "ow-l4-u9-vocab-1"
        }
      ],
      "tags": [
        "vocabulary",
        "target",
        "vocab-1",
        "force-and-motion",
        "OW4-U9-V1"
      ],
      "additionalExamples": [
        "What will happen if you don't hold on tight?",
        "Friction happens when two things rub together."
      ],
      "additionalExamplesJp": [
        "しっかりつかまらないと何が起こりますか。",
        "二つのものがこすれ合うと摩擦が起こります。"
      ]
    },
    {
      "id": "global_push",
      "type": "vocabulary",
      "word": "push",
      "normalizedWord": "push",
      "displayEmoji": "👉💥",
      "emojiDescription": "pointing hand with an impact mark showing a push",
      "partOfSpeech": "verb",
      "syllables": "push",
      "ipa": "pʊʃ",
      "meaning": "to press something away from you to make it move",
      "example": "You push the door to open it.",
      "exampleJp": "ドアを押して開けます。",
      "japanese": {
        "word": "押す",
        "reading": "おす",
        "meaning": "物を自分から離れる方向に力を加えて動かすこと。",
        "needsReview": true
      },
      "sources": [
        {
          "subject": "english",
          "course": "our-world",
          "level": 4,
          "unit": 9,
          "component": "vocab-1",
          "tag": "OW4-U9-V1",
          "lessonStatus": "draft",
          "lessonId": "ow-l4-u9-vocab-1"
        }
      ],
      "tags": [
        "vocabulary",
        "target",
        "vocab-1",
        "force-and-motion",
        "OW4-U9-V1"
      ],
      "additionalExamples": [
        "Push the swing gently to make it move.",
        "I can push the box across the floor."
      ],
      "additionalExamplesJp": [
        "ブランコをやさしく押して動かしてみましょう。",
        "私は箱を床の上で押すことができます。"
      ]
    },
    {
      "id": "global_pull",
      "type": "vocabulary",
      "word": "pull",
      "normalizedWord": "pull",
      "displayEmoji": "🤚⬅️",
      "emojiDescription": "hand pulling something toward the body",
      "partOfSpeech": "verb",
      "syllables": "pull",
      "ipa": "pʊl",
      "meaning": "to move something toward you using force",
      "example": "You pull the rope to bring it closer.",
      "exampleJp": "ロープを引いて近づけます。",
      "japanese": {
        "word": "引く",
        "reading": "ひく",
        "meaning": "物を自分の方に力を加えて動かすこと。",
        "needsReview": true
      },
      "sources": [
        {
          "subject": "english",
          "course": "our-world",
          "level": 4,
          "unit": 9,
          "component": "vocab-1",
          "tag": "OW4-U9-V1",
          "lessonStatus": "draft",
          "lessonId": "ow-l4-u9-vocab-1"
        }
      ],
      "tags": [
        "vocabulary",
        "target",
        "vocab-1",
        "force-and-motion",
        "OW4-U9-V1"
      ],
      "additionalExamples": [
        "Pull the door open, don't push it.",
        "The dog pulled on its leash."
      ],
      "additionalExamplesJp": [
        "ドアは押さずに引いて開けてください。",
        "その犬はリードを引っ張りました。"
      ]
    },
    {
      "id": "global_swing_toy",
      "type": "vocabulary",
      "word": "a swing",
      "normalizedWord": "swing",
      "displayEmoji": "🛝",
      "emojiDescription": "a playground swing set",
      "partOfSpeech": "noun",
      "syllables": "swing",
      "ipa": "swɪŋ",
      "meaning": "a seat that hangs from ropes or chains and moves back and forth",
      "example": "She likes to play on the swing at the park.",
      "exampleJp": "彼女は公園のブランコで遊ぶのが好きです。",
      "japanese": {
        "word": "ブランコ",
        "reading": "ぶらんこ",
        "meaning": "ロープや鎖でつるされた、前後に揺れる座席。",
        "needsReview": true
      },
      "sources": [
        {
          "subject": "english",
          "course": "our-world",
          "level": 4,
          "unit": 9,
          "component": "vocab-1",
          "tag": "OW4-U9-V1",
          "lessonStatus": "draft",
          "lessonId": "ow-l4-u9-vocab-1"
        }
      ],
      "tags": [
        "vocabulary",
        "target",
        "vocab-1",
        "force-and-motion",
        "OW4-U9-V1"
      ],
      "additionalExamples": [
        "My little brother wants to go higher on the swing.",
        "Two swings hang from the tall tree."
      ],
      "additionalExamplesJp": [
        "私の弟はブランコでもっと高く上がりたがっています。",
        "高い木から二つのブランコがつるされています。"
      ]
    },
    {
      "id": "global_skater",
      "type": "vocabulary",
      "word": "a skater",
      "normalizedWord": "skater",
      "displayEmoji": "⛸️",
      "emojiDescription": "an ice skate showing a person who skates",
      "partOfSpeech": "noun",
      "syllables": "skat-er",
      "ipa": "ˈskeɪtər",
      "meaning": "a person who moves on skates",
      "example": "The skater spins fast on the ice.",
      "exampleJp": "そのスケーターは氷の上で速く回転します。",
      "japanese": {
        "word": "スケーター",
        "reading": "すけーたー",
        "meaning": "スケートをする人。",
        "needsReview": true
      },
      "sources": [
        {
          "subject": "english",
          "course": "our-world",
          "level": 4,
          "unit": 9,
          "component": "vocab-1",
          "tag": "OW4-U9-V1",
          "lessonStatus": "draft",
          "lessonId": "ow-l4-u9-vocab-1"
        }
      ],
      "tags": [
        "vocabulary",
        "target",
        "vocab-1",
        "force-and-motion",
        "OW4-U9-V1"
      ],
      "additionalExamples": [
        "The skater balances on one leg before she spins.",
        "A good skater knows how to fall over safely."
      ],
      "additionalExamplesJp": [
        "そのスケーターは回転する前に片足でバランスを取ります。",
        "上手なスケーターは安全に転ぶ方法を知っています。"
      ]
    },
    {
      "id": "global_forward",
      "type": "vocabulary",
      "word": "forward",
      "normalizedWord": "forward",
      "displayEmoji": "⏩",
      "emojiDescription": "forward arrow",
      "partOfSpeech": "adverb",
      "syllables": "for-ward",
      "ipa": "ˈfɔːrwərd",
      "meaning": "toward the front; in the direction ahead of you",
      "example": "A push can move a skier forward.",
      "exampleJp": "押す力はスキーヤーを前に動かすことができます。",
      "japanese": {
        "word": "前へ",
        "reading": "まえへ",
        "meaning": "前の方向へ進むこと。",
        "needsReview": true
      },
      "sources": [
        {
          "subject": "english",
          "course": "our-world",
          "level": 4,
          "unit": 9,
          "component": "vocab-1",
          "tag": "OW4-U9-V1",
          "lessonStatus": "draft",
          "lessonId": "ow-l4-u9-vocab-1"
        }
      ],
      "tags": [
        "vocabulary",
        "target",
        "vocab-1",
        "force-and-motion",
        "OW4-U9-V1"
      ],
      "additionalExamples": [
        "Lean forward a little when you ride your bike uphill.",
        "The car moved forward slowly."
      ],
      "additionalExamplesJp": [
        "坂を自転車で登るときは少し前に傾いてください。",
        "その車はゆっくりと前に進みました。"
      ]
    },
    {
      "id": "global_backward",
      "type": "vocabulary",
      "word": "backward",
      "normalizedWord": "backward",
      "displayEmoji": "⏪",
      "emojiDescription": "backward arrow",
      "partOfSpeech": "adverb",
      "syllables": "back-ward",
      "ipa": "ˈbækwərd",
      "meaning": "toward the back; in the direction behind you",
      "example": "It can also move a skier backward.",
      "exampleJp": "それはスキーヤーを後ろにも動かすことができます。",
      "japanese": {
        "word": "後ろへ",
        "reading": "うしろへ",
        "meaning": "後ろの方向へ進むこと。",
        "needsReview": true
      },
      "sources": [
        {
          "subject": "english",
          "course": "our-world",
          "level": 4,
          "unit": 9,
          "component": "vocab-1",
          "tag": "OW4-U9-V1",
          "lessonStatus": "draft",
          "lessonId": "ow-l4-u9-vocab-1"
        }
      ],
      "tags": [
        "vocabulary",
        "target",
        "vocab-1",
        "force-and-motion",
        "OW4-U9-V1"
      ],
      "additionalExamples": [
        "He took two steps backward before he jumped.",
        "Don't walk backward near the stairs."
      ],
      "additionalExamplesJp": [
        "彼はジャンプする前に後ろに二歩下がりました。",
        "階段の近くで後ろ向きに歩かないでください。"
      ]
    },
    {
      "id": "global_spin",
      "type": "vocabulary",
      "word": "spin",
      "normalizedWord": "spin",
      "displayEmoji": "🌀",
      "emojiDescription": "a spiral swirl",
      "partOfSpeech": "verb",
      "syllables": "spin",
      "ipa": "spɪn",
      "meaning": "to turn around and around quickly in a circle",
      "example": "The skaters spin fast on the ice.",
      "exampleJp": "スケーターたちは氷の上で速く回転します。",
      "japanese": {
        "word": "回転する",
        "reading": "かいてんする",
        "meaning": "円を描くように速く回ること。",
        "needsReview": true
      },
      "sources": [
        {
          "subject": "english",
          "course": "our-world",
          "level": 4,
          "unit": 9,
          "component": "vocab-1",
          "tag": "OW4-U9-V1",
          "lessonStatus": "draft",
          "lessonId": "ow-l4-u9-vocab-1"
        }
      ],
      "tags": [
        "vocabulary",
        "target",
        "vocab-1",
        "force-and-motion",
        "OW4-U9-V1"
      ],
      "additionalExamples": [
        "The gyroscope's rings spin in every direction.",
        "Spin the wheel and see where it stops."
      ],
      "additionalExamplesJp": [
        "ジャイロスコープの輪はあらゆる方向に回転します。",
        "車輪を回転させて、どこで止まるか見てみましょう。"
      ]
    },
    {
      "id": "global_fall_over",
      "type": "vocabulary",
      "word": "fall over",
      "normalizedWord": "fall over",
      "displayEmoji": "💥⬇️",
      "emojiDescription": "an impact with a downward arrow showing someone falling down",
      "partOfSpeech": "verb",
      "syllables": "fall o-ver",
      "ipa": "fɔːl ˈoʊvər",
      "meaning": "to lose your balance and drop down",
      "example": "The skaters don't fall over because they know how to balance.",
      "exampleJp": "スケーターたちはバランスの取り方を知っているので転びません。",
      "japanese": {
        "word": "転ぶ",
        "reading": "ころぶ",
        "meaning": "バランスを失って倒れること。",
        "needsReview": true
      },
      "sources": [
        {
          "subject": "english",
          "course": "our-world",
          "level": 4,
          "unit": 9,
          "component": "vocab-1",
          "tag": "OW4-U9-V1",
          "lessonStatus": "draft",
          "lessonId": "ow-l4-u9-vocab-1"
        }
      ],
      "tags": [
        "vocabulary",
        "target",
        "vocab-1",
        "force-and-motion",
        "OW4-U9-V1"
      ],
      "additionalExamples": [
        "Hold the rail so you don't fall over on the bus.",
        "A tower of blocks can fall over with a small push."
      ],
      "additionalExamplesJp": [
        "バスの中で転ばないように手すりをつかんでください。",
        "積み木のタワーは小さく押すだけで倒れることがあります。"
      ]
    },
    {
      "id": "global_balance",
      "type": "vocabulary",
      "word": "balance",
      "normalizedWord": "balance",
      "displayEmoji": "⚖️",
      "emojiDescription": "a balance scale",
      "partOfSpeech": "noun/verb",
      "syllables": "bal-ance",
      "ipa": "ˈbæləns",
      "meaning": "the ability to stay steady and not fall over",
      "example": "Can you balance on one leg?",
      "exampleJp": "片足でバランスを取れますか。",
      "japanese": {
        "word": "バランス",
        "reading": "ばらんす",
        "meaning": "体を安定させて倒れないようにすること。",
        "needsReview": true
      },
      "sources": [
        {
          "subject": "english",
          "course": "our-world",
          "level": 4,
          "unit": 9,
          "component": "vocab-1",
          "tag": "OW4-U9-V1",
          "lessonStatus": "draft",
          "lessonId": "ow-l4-u9-vocab-1"
        }
      ],
      "tags": [
        "vocabulary",
        "target",
        "vocab-1",
        "force-and-motion",
        "OW4-U9-V1"
      ],
      "additionalExamples": [
        "Riding a bike takes good balance.",
        "She lost her balance and grabbed the rail."
      ],
      "additionalExamplesJp": [
        "自転車に乗るにはよいバランス感覚が必要です。",
        "彼女はバランスを崩して手すりをつかみました。"
      ]
    },
    {
      "id": "global_down",
      "type": "vocabulary",
      "word": "down",
      "normalizedWord": "down",
      "displayEmoji": "⬇️",
      "emojiDescription": "a down arrow",
      "partOfSpeech": "adverb",
      "syllables": "down",
      "ipa": "daʊn",
      "meaning": "toward a lower place; from a higher position to a lower one",
      "example": "Skaters push down hard on their skates.",
      "exampleJp": "スケーターたちはスケート靴を強く下に押します。",
      "japanese": {
        "word": "下へ",
        "reading": "したへ",
        "meaning": "高い場所から低い場所への方向。",
        "needsReview": true
      },
      "sources": [
        {
          "subject": "english",
          "course": "our-world",
          "level": 4,
          "unit": 9,
          "component": "vocab-1",
          "tag": "OW4-U9-V1",
          "lessonStatus": "draft",
          "lessonId": "ow-l4-u9-vocab-1"
        }
      ],
      "tags": [
        "vocabulary",
        "target",
        "vocab-1",
        "force-and-motion",
        "OW4-U9-V1"
      ],
      "additionalExamples": [
        "Gravity pulls the ball down to the ground.",
        "Sit down and put on your safety bar."
      ],
      "additionalExamplesJp": [
        "重力はボールを地面に向かって下に引きます。",
        "座ってセーフティーバーをつけてください。"
      ]
    },
    {
      "id": "global_connect",
      "type": "vocabulary",
      "word": "connect",
      "normalizedWord": "connect",
      "displayEmoji": "🔗",
      "emojiDescription": "a chain link",
      "partOfSpeech": "verb",
      "syllables": "con-nect",
      "ipa": "kəˈnɛkt",
      "meaning": "to join two things together",
      "example": "The skates connect with the ice.",
      "exampleJp": "スケート靴は氷とつながります。",
      "japanese": {
        "word": "つながる",
        "reading": "つながる",
        "meaning": "二つのものを結びつけること。",
        "needsReview": true
      },
      "sources": [
        {
          "subject": "english",
          "course": "our-world",
          "level": 4,
          "unit": 9,
          "component": "vocab-1",
          "tag": "OW4-U9-V1",
          "lessonStatus": "draft",
          "lessonId": "ow-l4-u9-vocab-1"
        }
      ],
      "tags": [
        "vocabulary",
        "target",
        "vocab-1",
        "force-and-motion",
        "OW4-U9-V1"
      ],
      "additionalExamples": [
        "The two circles of the thaumatrope connect with string.",
        "This wire connects the machine to the wall."
      ],
      "additionalExamplesJp": [
        "ソーマトロープの二つの円は糸でつながっています。",
        "このコードは機械を壁につないでいます。"
      ]
    },
    {
      "id": "global_rub",
      "type": "vocabulary",
      "word": "rub",
      "normalizedWord": "rub",
      "displayEmoji": "🤲💫",
      "emojiDescription": "hands rubbing together",
      "partOfSpeech": "verb",
      "syllables": "rub",
      "ipa": "rʌb",
      "meaning": "to move one thing back and forth against another",
      "example": "The ice and skates rub together.",
      "exampleJp": "氷とスケート靴がこすれ合います。",
      "japanese": {
        "word": "こする",
        "reading": "こする",
        "meaning": "物を他の物に何度も押し当てて動かすこと。",
        "needsReview": true
      },
      "sources": [
        {
          "subject": "english",
          "course": "our-world",
          "level": 4,
          "unit": 9,
          "component": "vocab-1",
          "tag": "OW4-U9-V1",
          "lessonStatus": "draft",
          "lessonId": "ow-l4-u9-vocab-1"
        }
      ],
      "tags": [
        "vocabulary",
        "target",
        "vocab-1",
        "force-and-motion",
        "OW4-U9-V1"
      ],
      "additionalExamples": [
        "Rub your hands together to warm them up.",
        "Don't rub your eyes when they hurt."
      ],
      "additionalExamplesJp": [
        "手をこすり合わせて温めましょう。",
        "目が痛いときはこすらないでください。"
      ]
    },
    {
      "id": "global_friction",
      "type": "vocabulary",
      "word": "friction",
      "normalizedWord": "friction",
      "displayEmoji": "🤚🔥",
      "emojiDescription": "a rubbing hand with a flame showing heat from friction",
      "partOfSpeech": "noun",
      "syllables": "fric-tion",
      "ipa": "ˈfrɪkʃən",
      "meaning": "the force created when two things rub together",
      "example": "When two things rub together, it's called friction.",
      "exampleJp": "二つのものがこすれ合うと、それは摩擦と呼ばれます。",
      "japanese": {
        "word": "摩擦",
        "reading": "まさつ",
        "meaning": "二つの物がこすれ合うときに生じる力。",
        "needsReview": true
      },
      "sources": [
        {
          "subject": "english",
          "course": "our-world",
          "level": 4,
          "unit": 9,
          "component": "vocab-1",
          "tag": "OW4-U9-V1",
          "lessonStatus": "draft",
          "lessonId": "ow-l4-u9-vocab-1"
        }
      ],
      "tags": [
        "vocabulary",
        "target",
        "vocab-1",
        "force-and-motion",
        "OW4-U9-V1"
      ],
      "additionalExamples": [
        "The brakes use friction to stop the bike.",
        "Friction between your shoes and the floor keeps you from slipping."
      ],
      "additionalExamplesJp": [
        "ブレーキは摩擦を使って自転車を止めます。",
        "靴と床の間の摩擦があなたが滑るのを防ぎます。"
      ]
    },
    {
      "id": "global_athlete",
      "type": "content",
      "word": "an athlete",
      "normalizedWord": "athlete",
      "displayEmoji": "🏃",
      "emojiDescription": "a running athlete",
      "partOfSpeech": "noun",
      "syllables": "ath-lete",
      "ipa": "ˈæθliːt",
      "meaning": "a person who is skilled at sports and physical activities",
      "example": "The video shows how an athlete uses force to move.",
      "exampleJp": "この動画は、あるアスリートがどのように力を使って動くかを示しています。",
      "japanese": {
        "word": "アスリート",
        "reading": "あすりーと",
        "meaning": "スポーツが得意な人。",
        "needsReview": true
      },
      "sources": [
        {
          "subject": "english",
          "course": "our-world",
          "level": 4,
          "unit": 9,
          "component": "vocab-1",
          "tag": "OW4-U9-V1",
          "lessonStatus": "draft",
          "lessonId": "ow-l4-u9-vocab-1"
        }
      ],
      "tags": [
        "content",
        "vocab-1",
        "force-and-motion",
        "OW4-U9-V1"
      ],
      "additionalExamples": [
        "Every athlete on the team practices every day.",
        "The athlete uses a lot of force to jump high."
      ],
      "additionalExamplesJp": [
        "チームのすべてのアスリートは毎日練習します。",
        "そのアスリートは高くジャンプするために大きな力を使います。"
      ]
    },
    {
      "id": "global_jump",
      "type": "content",
      "word": "jump",
      "normalizedWord": "jump",
      "displayEmoji": "🤸‍♀️⬆️",
      "emojiDescription": "a person jumping upward",
      "partOfSpeech": "verb",
      "syllables": "jump",
      "ipa": "dʒʌmp",
      "meaning": "to push yourself off the ground into the air",
      "example": "Look at this skier jump off the hill.",
      "exampleJp": "この選手が丘からジャンプするのを見てください。",
      "japanese": {
        "word": "ジャンプする",
        "reading": "じゃんぷする",
        "meaning": "地面を蹴って空中に上がること。",
        "needsReview": true
      },
      "sources": [
        {
          "subject": "english",
          "course": "our-world",
          "level": 4,
          "unit": 9,
          "component": "vocab-1",
          "tag": "OW4-U9-V1",
          "lessonStatus": "draft",
          "lessonId": "ow-l4-u9-vocab-1"
        }
      ],
      "tags": [
        "content",
        "vocab-1",
        "force-and-motion",
        "OW4-U9-V1"
      ],
      "additionalExamples": [
        "Bend your knees before you jump.",
        "The dog can jump over the fence."
      ],
      "additionalExamplesJp": [
        "ジャンプする前にひざを曲げてください。",
        "その犬はフェンスを飛び越えることができます。"
      ]
    },
    {
      "id": "global_skier",
      "type": "content",
      "word": "a skier",
      "normalizedWord": "skier",
      "displayEmoji": "⛷️",
      "emojiDescription": "a person skiing",
      "partOfSpeech": "noun",
      "syllables": "ski-er",
      "ipa": "ˈskiːər",
      "meaning": "a person who moves on skis over snow",
      "example": "Look at this skier. To move, a skier pushes on the snow.",
      "exampleJp": "このスキーヤーを見てください。動くために、スキーヤーは雪を押します。",
      "japanese": {
        "word": "スキーヤー",
        "reading": "すきーやー",
        "meaning": "スキーで雪の上を進む人。",
        "needsReview": true
      },
      "sources": [
        {
          "subject": "english",
          "course": "our-world",
          "level": 4,
          "unit": 9,
          "component": "vocab-1",
          "tag": "OW4-U9-V1",
          "lessonStatus": "draft",
          "lessonId": "ow-l4-u9-vocab-1"
        }
      ],
      "tags": [
        "content",
        "vocab-1",
        "force-and-motion",
        "OW4-U9-V1"
      ],
      "additionalExamples": [
        "The skier uses force to move forward on the snow.",
        "A skier needs good balance to turn quickly."
      ],
      "additionalExamplesJp": [
        "そのスキーヤーは雪の上を前に進むために力を使います。",
        "スキーヤーは素早く曲がるためによいバランス感覚が必要です。"
      ]
    },
    {
      "id": "global_away_from",
      "type": "vocabulary",
      "word": "away from",
      "normalizedWord": "away from",
      "displayEmoji": "🚶‍♂️↗️",
      "emojiDescription": "a person walking away in an outward direction",
      "partOfSpeech": "preposition",
      "syllables": "a-way from",
      "ipa": "əˈweɪ frʌm",
      "meaning": "moving in the opposite direction from something or someone",
      "example": "He is walking away from the music because it's too loud.",
      "exampleJp": "音楽がうるさいので、彼はそこから離れて歩いています。",
      "japanese": {
        "word": "〜から離れて",
        "reading": "〜からはなれて",
        "meaning": "ある物や人から遠ざかる方向。",
        "needsReview": true
      },
      "sources": [
        {
          "subject": "english",
          "course": "our-world",
          "level": 4,
          "unit": 9,
          "component": "vocab-2",
          "tag": "OW4-U9-V2",
          "lessonStatus": "draft",
          "lessonId": "ow-l4-u9-vocab-2"
        }
      ],
      "tags": [
        "vocabulary",
        "target",
        "vocab-2",
        "direction",
        "OW4-U9-V2"
      ],
      "additionalExamples": [
        "Walk away from the pool if you hear thunder.",
        "The ball rolled away from the house."
      ],
      "additionalExamplesJp": [
        "雷が聞こえたらプールから離れて歩いてください。",
        "ボールは家から離れて転がっていきました。"
      ]
    },
    {
      "id": "global_direction",
      "type": "vocabulary",
      "word": "direction",
      "normalizedWord": "direction",
      "displayEmoji": "🧭",
      "emojiDescription": "a compass",
      "partOfSpeech": "noun",
      "syllables": "di-rec-tion",
      "ipa": "dəˈrɛkʃən",
      "meaning": "the way something moves or points",
      "example": "Don't go in that direction, it's too loud.",
      "exampleJp": "その方向に行かないで、うるさいから。",
      "japanese": {
        "word": "方向",
        "reading": "ほうこう",
        "meaning": "物が動く、または向いている道筋。",
        "needsReview": true
      },
      "sources": [
        {
          "subject": "english",
          "course": "our-world",
          "level": 4,
          "unit": 9,
          "component": "vocab-2",
          "tag": "OW4-U9-V2",
          "lessonStatus": "draft",
          "lessonId": "ow-l4-u9-vocab-2"
        }
      ],
      "tags": [
        "vocabulary",
        "target",
        "vocab-2",
        "direction",
        "OW4-U9-V2"
      ],
      "additionalExamples": [
        "Which direction is the wind blowing?",
        "Follow the arrow to find the right direction."
      ],
      "additionalExamplesJp": [
        "風はどちらの方向に吹いていますか。",
        "正しい方向を見つけるために矢印に従ってください。"
      ]
    },
    {
      "id": "global_toward",
      "type": "vocabulary",
      "word": "toward",
      "normalizedWord": "toward",
      "displayEmoji": "🚶‍♂️↘️",
      "emojiDescription": "a person walking toward a target",
      "partOfSpeech": "preposition",
      "syllables": "to-ward",
      "ipa": "təˈwɔːrd",
      "meaning": "moving in the direction of something or someone",
      "example": "She is riding toward the swings because she wants to play on them.",
      "exampleJp": "彼女はブランコで遊びたいので、そちらに向かって進んでいます。",
      "japanese": {
        "word": "〜に向かって",
        "reading": "〜にむかって",
        "meaning": "ある物や人に近づく方向。",
        "needsReview": true
      },
      "sources": [
        {
          "subject": "english",
          "course": "our-world",
          "level": 4,
          "unit": 9,
          "component": "vocab-2",
          "tag": "OW4-U9-V2",
          "lessonStatus": "draft",
          "lessonId": "ow-l4-u9-vocab-2"
        }
      ],
      "tags": [
        "vocabulary",
        "target",
        "vocab-2",
        "direction",
        "OW4-U9-V2"
      ],
      "additionalExamples": [
        "The dog ran toward its owner.",
        "Lean toward the front when the roller coaster goes up."
      ],
      "additionalExamplesJp": [
        "その犬は飼い主に向かって走りました。",
        "ジェットコースターが上がるときは前の方に体を傾けてください。"
      ]
    },
    {
      "id": "global_lean",
      "type": "vocabulary",
      "word": "lean",
      "normalizedWord": "lean",
      "displayEmoji": "🚵",
      "emojiDescription": "a mountain biker leaning their body into a turn",
      "partOfSpeech": "verb",
      "syllables": "lean",
      "ipa": "liːn",
      "meaning": "to bend your body to one side",
      "example": "When you ride your bicycle and turn left, you lean to the left.",
      "exampleJp": "自転車に乗って左に曲がるとき、あなたは左に体を傾けます。",
      "japanese": {
        "word": "傾く",
        "reading": "かたむく",
        "meaning": "体を一方向に少し傾けること。",
        "needsReview": true
      },
      "sources": [
        {
          "subject": "english",
          "course": "our-world",
          "level": 4,
          "unit": 9,
          "component": "vocab-2",
          "tag": "OW4-U9-V2",
          "lessonStatus": "draft",
          "lessonId": "ow-l4-u9-vocab-2"
        }
      ],
      "tags": [
        "vocabulary",
        "target",
        "vocab-2",
        "direction",
        "OW4-U9-V2"
      ],
      "additionalExamples": [
        "She had to lean forward to see the road.",
        "Don't lean too far or you will fall over."
      ],
      "additionalExamplesJp": [
        "彼女は道を見るために前に体を傾けなければなりませんでした。",
        "傾きすぎると転んでしまうので気をつけてください。"
      ]
    },
    {
      "id": "global_gravity",
      "type": "vocabulary",
      "word": "gravity",
      "normalizedWord": "gravity",
      "displayEmoji": "🌍⬇️",
      "emojiDescription": "the Earth with a downward arrow",
      "partOfSpeech": "noun",
      "syllables": "grav-i-ty",
      "ipa": "ˈɡrævəti",
      "meaning": "the force that pulls things down toward the Earth",
      "example": "When you throw a ball, gravity pulls it toward the Earth.",
      "exampleJp": "ボールを投げると、重力がそれを地球の方に引きます。",
      "japanese": {
        "word": "重力",
        "reading": "じゅうりょく",
        "meaning": "物を地球の中心に向かって引く力。",
        "needsReview": true
      },
      "sources": [
        {
          "subject": "english",
          "course": "our-world",
          "level": 4,
          "unit": 9,
          "component": "vocab-2",
          "tag": "OW4-U9-V2",
          "lessonStatus": "draft",
          "lessonId": "ow-l4-u9-vocab-2"
        }
      ],
      "tags": [
        "vocabulary",
        "target",
        "vocab-2",
        "direction",
        "OW4-U9-V2"
      ],
      "additionalExamples": [
        "Gravity keeps your feet on the ground.",
        "Without gravity, objects would float away."
      ],
      "additionalExamplesJp": [
        "重力はあなたの足を地面につけたままにします。",
        "重力がなければ、物は浮いていってしまうでしょう。"
      ]
    },
    {
      "id": "global_merry_go_round",
      "type": "content",
      "word": "merry-go-round",
      "normalizedWord": "merry-go-round",
      "displayEmoji": "🎠",
      "emojiDescription": "a merry-go-round horse",
      "partOfSpeech": "noun",
      "syllables": "mer-ry-go-round",
      "ipa": "ˈmɛri ɡoʊ raʊnd",
      "meaning": "a round platform with seats that turns around and around for fun",
      "example": "Two boys are on a merry-go-round, going around and around.",
      "exampleJp": "二人の少年がメリーゴーランドに乗って、ぐるぐる回っています。",
      "japanese": {
        "word": "メリーゴーランド",
        "reading": "めりーごーらんど",
        "meaning": "座って乗り、ぐるぐる回る遊具。",
        "needsReview": true
      },
      "sources": [
        {
          "subject": "english",
          "course": "our-world",
          "level": 4,
          "unit": 9,
          "component": "grammar-1",
          "tag": "OW4-U9-G1",
          "lessonStatus": "draft",
          "lessonId": "ow-l4-u9-grammar-1"
        }
      ],
      "tags": [
        "content",
        "grammar-1",
        "playground",
        "OW4-U9-G1"
      ],
      "additionalExamples": [
        "The merry-go-round spins slowly at first, then faster.",
        "Three children are riding the merry-go-round together."
      ],
      "additionalExamplesJp": [
        "メリーゴーランドは最初はゆっくり、その後速く回転します。",
        "三人の子どもたちが一緒にメリーゴーランドに乗っています。"
      ]
    },
    {
      "id": "global_seesaw",
      "type": "content",
      "word": "seesaw",
      "normalizedWord": "seesaw",
      "displayEmoji": "⬆️⬇️",
      "emojiDescription": "up and down arrows showing a seesaw's motion",
      "partOfSpeech": "noun",
      "syllables": "see-saw",
      "ipa": "ˈsiːsɔː",
      "meaning": "a long board that goes up and down when two people sit on each end",
      "example": "Two boys are on a seesaw. When one goes down, the other goes up.",
      "exampleJp": "二人の少年がシーソーに乗っています。一人が下がると、もう一人が上がります。",
      "japanese": {
        "word": "シーソー",
        "reading": "しーそー",
        "meaning": "両端に人が座り、上下に動く遊具。",
        "needsReview": true
      },
      "sources": [
        {
          "subject": "english",
          "course": "our-world",
          "level": 4,
          "unit": 9,
          "component": "grammar-1",
          "tag": "OW4-U9-G1",
          "lessonStatus": "draft",
          "lessonId": "ow-l4-u9-grammar-1"
        }
      ],
      "tags": [
        "content",
        "grammar-1",
        "playground",
        "OW4-U9-G1"
      ],
      "additionalExamples": [
        "A heavier person should sit closer to the center of the seesaw.",
        "The seesaw creaks every time it goes up and down."
      ],
      "additionalExamplesJp": [
        "体重が重い人はシーソーの中心に近く座るべきです。",
        "そのシーソーは上下するたびにきしみます。"
      ]
    },
    {
      "id": "global_skateboarder",
      "type": "content",
      "word": "skateboarder",
      "normalizedWord": "skateboarder",
      "displayEmoji": "🛹",
      "emojiDescription": "a skateboard",
      "partOfSpeech": "noun",
      "syllables": "skate-board-er",
      "ipa": "ˈskeɪtbɔːrdər",
      "meaning": "a person who rides a skateboard",
      "example": "The more the skateboarder pushes, the faster he moves forward.",
      "exampleJp": "スケートボーダーが押せば押すほど、彼はより速く前に進みます。",
      "japanese": {
        "word": "スケートボーダー",
        "reading": "すけーとぼーだー",
        "meaning": "スケートボードに乗る人。",
        "needsReview": true
      },
      "sources": [
        {
          "subject": "english",
          "course": "our-world",
          "level": 4,
          "unit": 9,
          "component": "grammar-1",
          "tag": "OW4-U9-G1",
          "lessonStatus": "draft",
          "lessonId": "ow-l4-u9-grammar-1"
        }
      ],
      "tags": [
        "content",
        "grammar-1",
        "playground",
        "OW4-U9-G1"
      ],
      "additionalExamples": [
        "The skateboarder practices new tricks every afternoon.",
        "A skateboarder needs good balance to stay on the board."
      ],
      "additionalExamplesJp": [
        "そのスケートボーダーは毎日午後に新しい技を練習します。",
        "スケートボーダーはボードの上にとどまるためによいバランス感覚が必要です。"
      ]
    },
    {
      "id": "global_tetherball",
      "type": "content",
      "word": "tetherball",
      "normalizedWord": "tetherball",
      "displayEmoji": "🎾🔗",
      "emojiDescription": "a tennis ball linked to a pole with a chain",
      "partOfSpeech": "noun",
      "syllables": "teth-er-ball",
      "ipa": "ˈtɛðərbɔːl",
      "meaning": "a game where you hit a ball tied to a pole with a rope",
      "example": "Two people play tetherball. One person hits the ball to the right.",
      "exampleJp": "二人でテザーボールをします。一人がボールを右に打ちます。",
      "japanese": {
        "word": "テザーボール",
        "reading": "てざーぼーる",
        "meaning": "ロープでポールにつながれたボールを打ち合うゲーム。",
        "needsReview": true
      },
      "sources": [
        {
          "subject": "english",
          "course": "our-world",
          "level": 4,
          "unit": 9,
          "component": "grammar-2",
          "tag": "OW4-U9-G2",
          "lessonStatus": "draft",
          "lessonId": "ow-l4-u9-grammar-2"
        }
      ],
      "tags": [
        "content",
        "grammar-2",
        "games",
        "OW4-U9-G2"
      ],
      "additionalExamples": [
        "We play tetherball at recess every day.",
        "The rope on the tetherball got twisted around the pole."
      ],
      "additionalExamplesJp": [
        "私たちは休み時間に毎日テザーボールをします。",
        "テザーボールのロープはポールに巻きついてねじれました。"
      ]
    },
    {
      "id": "global_safety_bar",
      "type": "content",
      "word": "safety bar",
      "normalizedWord": "safety bar",
      "displayEmoji": "🔒🎢",
      "emojiDescription": "a lock with a roller coaster showing a safety bar",
      "partOfSpeech": "noun",
      "syllables": "safe-ty bar",
      "ipa": "ˈseɪfti bɑːr",
      "meaning": "a bar you hold and pull down to stay safe in a moving ride",
      "example": "Sit in the car and pull down the safety bar.",
      "exampleJp": "車に座って、セーフティーバーを引き下げてください。",
      "japanese": {
        "word": "セーフティーバー",
        "reading": "せーふてぃーばー",
        "meaning": "乗り物の中で体を支える安全のための棒。",
        "needsReview": true
      },
      "sources": [
        {
          "subject": "english",
          "course": "our-world",
          "level": 4,
          "unit": 9,
          "component": "reading",
          "tag": "OW4-U9-RD",
          "lessonStatus": "draft",
          "lessonId": "ow-l4-u9-reading"
        }
      ],
      "tags": [
        "content",
        "reading",
        "roller-coaster",
        "OW4-U9-RD"
      ],
      "additionalExamples": [
        "Check that your safety bar is locked before the ride starts.",
        "The safety bar keeps you in your seat during the loop."
      ],
      "additionalExamplesJp": [
        "乗り物が始まる前にセーフティーバーがロックされているか確認してください。",
        "セーフティーバーはループの間あなたを座席に留めます。"
      ]
    },
    {
      "id": "global_steep",
      "type": "content",
      "word": "steep",
      "normalizedWord": "steep",
      "displayEmoji": "⛰️",
      "emojiDescription": "a steep mountain slope",
      "partOfSpeech": "adjective",
      "syllables": "steep",
      "ipa": "stiːp",
      "meaning": "rising or falling very sharply, like a hill",
      "example": "First you go up a steep hill.",
      "exampleJp": "最初に急な坂を登ります。",
      "japanese": {
        "word": "急な",
        "reading": "きゅうな",
        "meaning": "角度が大きく、上りや下りが急であること。",
        "needsReview": true
      },
      "sources": [
        {
          "subject": "english",
          "course": "our-world",
          "level": 4,
          "unit": 9,
          "component": "reading",
          "tag": "OW4-U9-RD",
          "lessonStatus": "draft",
          "lessonId": "ow-l4-u9-reading"
        }
      ],
      "tags": [
        "content",
        "reading",
        "roller-coaster",
        "OW4-U9-RD"
      ],
      "additionalExamples": [
        "The roller coaster's first hill is very steep.",
        "It's hard to climb a steep hill on a bike."
      ],
      "additionalExamplesJp": [
        "そのジェットコースターの最初の坂はとても急です。",
        "自転車で急な坂を登るのは大変です。"
      ]
    },
    {
      "id": "global_centripetal_force",
      "type": "content",
      "word": "centripetal force",
      "normalizedWord": "centripetal force",
      "displayEmoji": "🎡🔄",
      "emojiDescription": "a Ferris wheel with a circular arrow showing a force pulling something in a circle",
      "partOfSpeech": "noun",
      "syllables": "cen-trip-e-tal force",
      "ipa": "sɛnˈtrɪpətəl fɔːrs",
      "meaning": "the force that keeps something moving in a circle",
      "example": "A force called centripetal force keeps you moving in a circle.",
      "exampleJp": "求心力と呼ばれる力が、あなたを円を描くように動かし続けます。",
      "japanese": {
        "word": "求心力",
        "reading": "きゅうしんりょく",
        "meaning": "物を円の中心に向かって引き、円運動を続けさせる力。",
        "needsReview": true
      },
      "sources": [
        {
          "subject": "english",
          "course": "our-world",
          "level": 4,
          "unit": 9,
          "component": "reading",
          "tag": "OW4-U9-RD",
          "lessonStatus": "draft",
          "lessonId": "ow-l4-u9-reading"
        }
      ],
      "tags": [
        "content",
        "reading",
        "roller-coaster",
        "OW4-U9-RD"
      ],
      "additionalExamples": [
        "Centripetal force keeps the car on the track during the loop.",
        "Without centripetal force, you would fly off the ride."
      ],
      "additionalExamplesJp": [
        "求心力はループの間、車をトラックの上にとどめます。",
        "求心力がなければ、あなたは乗り物から飛び出してしまうでしょう。"
      ]
    },
    {
      "id": "global_inertia",
      "type": "content",
      "word": "inertia",
      "normalizedWord": "inertia",
      "displayEmoji": "➡️🛑",
      "emojiDescription": "a forward arrow hitting a stop sign showing resistance to changing motion",
      "partOfSpeech": "noun",
      "syllables": "in-er-tia",
      "ipa": "ɪˈnɜːrʃə",
      "meaning": "the tendency of something moving to keep moving",
      "example": "Your body wants to continue moving. That is called inertia.",
      "exampleJp": "あなたの体は動き続けようとします。それが慣性と呼ばれるものです。",
      "japanese": {
        "word": "慣性",
        "reading": "かんせい",
        "meaning": "動いているものがそのまま動き続けようとする性質。",
        "needsReview": true
      },
      "sources": [
        {
          "subject": "english",
          "course": "our-world",
          "level": 4,
          "unit": 9,
          "component": "reading",
          "tag": "OW4-U9-RD",
          "lessonStatus": "draft",
          "lessonId": "ow-l4-u9-reading"
        }
      ],
      "tags": [
        "content",
        "reading",
        "roller-coaster",
        "OW4-U9-RD"
      ],
      "additionalExamples": [
        "Inertia makes it hard to stop a heavy object quickly.",
        "Because of inertia, you keep moving forward when the car stops suddenly."
      ],
      "additionalExamplesJp": [
        "慣性は重い物を素早く止めるのを難しくします。",
        "慣性のため、車が急に止まるとあなたは前に動き続けます。"
      ]
    },
    {
      "id": "global_experience",
      "type": "content",
      "word": "experience",
      "normalizedWord": "experience",
      "displayEmoji": "🙌🎢",
      "emojiDescription": "raised hands with a roller coaster showing feeling something happen to you",
      "partOfSpeech": "verb",
      "syllables": "ex-pe-ri-ence",
      "ipa": "ɪkˈspɪriəns",
      "meaning": "something that happens to you that you feel or notice",
      "example": "You experience these forces every day.",
      "exampleJp": "あなたは毎日これらの力を経験します。",
      "japanese": {
        "word": "経験する",
        "reading": "けいけんする",
        "meaning": "自分が実際に感じたり体験したりすること。",
        "needsReview": true
      },
      "sources": [
        {
          "subject": "english",
          "course": "our-world",
          "level": 4,
          "unit": 9,
          "component": "reading",
          "tag": "OW4-U9-RD",
          "lessonStatus": "draft",
          "lessonId": "ow-l4-u9-reading"
        }
      ],
      "tags": [
        "content",
        "reading",
        "roller-coaster",
        "OW4-U9-RD"
      ],
      "additionalExamples": [
        "You experience friction every time you use the brakes.",
        "Riding a roller coaster is an exciting experience."
      ],
      "additionalExamplesJp": [
        "ブレーキを使うたびにあなたは摩擦を経験します。",
        "ジェットコースターに乗ることはわくわくする経験です。"
      ]
    },
    {
      "id": "global_figure_skating",
      "type": "related",
      "word": "figure skating",
      "normalizedWord": "figure skating",
      "displayEmoji": "⛸️✨",
      "emojiDescription": "an ice skate with sparkles for the artistic sport",
      "partOfSpeech": "noun",
      "syllables": "fig-ure skat-ing",
      "ipa": "ˈfɪɡjər ˈskeɪtɪŋ",
      "meaning": "a sport where skaters move and spin on ice in patterns",
      "example": "The photo shows figure skating, with a pair spinning together on the ice.",
      "exampleJp": "写真はフィギュアスケートを示しており、ペアが氷の上で一緒に回転しています。",
      "japanese": {
        "word": "フィギュアスケート",
        "reading": "ふぃぎゅあすけーと",
        "meaning": "氷の上で模様を描くように滑ったり回転したりするスポーツ。",
        "needsReview": true
      },
      "sources": [
        {
          "subject": "english",
          "course": "our-world",
          "level": 4,
          "unit": 9,
          "component": "vocab-1",
          "tag": "OW4-U9-V1",
          "lessonStatus": "draft",
          "lessonId": "ow-l4-u9-vocab-1"
        }
      ],
      "tags": [
        "related",
        "vocab-1",
        "force-and-motion",
        "OW4-U9-V1"
      ],
      "additionalExamples": [
        "Figure skating combines jumps, spins, and music.",
        "She has practiced figure skating since she was five."
      ],
      "additionalExamplesJp": [
        "フィギュアスケートはジャンプ、回転、音楽を組み合わせたものです。",
        "彼女は5歳のときからフィギュアスケートを練習しています。"
      ]
    },
    {
      "id": "global_freestyle_skiing",
      "type": "related",
      "word": "freestyle skiing",
      "normalizedWord": "freestyle skiing",
      "displayEmoji": "⛷️🕺",
      "emojiDescription": "a skier with a dancing figure showing tricks in the air",
      "partOfSpeech": "noun",
      "syllables": "free-style ski-ing",
      "ipa": "ˈfriːstaɪl ˈskiːɪŋ",
      "meaning": "a sport where skiers do jumps and tricks in the air",
      "example": "Freestyle skiing includes jumps of different kinds and heights.",
      "exampleJp": "フリースタイルスキーには、さまざまな種類や高さのジャンプがあります。",
      "japanese": {
        "word": "フリースタイルスキー",
        "reading": "ふりーすたいるすきー",
        "meaning": "ジャンプや技を見せるスキーの競技。",
        "needsReview": true
      },
      "sources": [
        {
          "subject": "english",
          "course": "our-world",
          "level": 4,
          "unit": 9,
          "component": "vocab-1",
          "tag": "OW4-U9-V1",
          "lessonStatus": "draft",
          "lessonId": "ow-l4-u9-vocab-1"
        }
      ],
      "tags": [
        "related",
        "vocab-1",
        "force-and-motion",
        "OW4-U9-V1"
      ],
      "additionalExamples": [
        "Freestyle skiing judges look at the height of each jump.",
        "He wants to try freestyle skiing this winter."
      ],
      "additionalExamplesJp": [
        "フリースタイルスキーの審判は各ジャンプの高さを見ます。",
        "彼はこの冬フリースタイルスキーに挑戦したいと思っています。"
      ]
    },
    {
      "id": "global_ice_rink",
      "type": "related",
      "word": "ice rink",
      "normalizedWord": "ice rink",
      "displayEmoji": "🧊⛸️",
      "emojiDescription": "an ice cube with a skate",
      "partOfSpeech": "noun",
      "syllables": "ice rink",
      "ipa": "ˈaɪs rɪŋk",
      "meaning": "a flat, icy surface where people skate",
      "example": "Skaters practice their spins at the ice rink.",
      "exampleJp": "スケーターたちはアイスリンクでスピンの練習をします。",
      "japanese": {
        "word": "アイスリンク",
        "reading": "あいすりんく",
        "meaning": "人々がスケートをする、氷でできた広い場所。",
        "needsReview": true
      },
      "sources": [
        {
          "subject": "english",
          "course": "our-world",
          "level": 4,
          "unit": 9,
          "component": "vocab-1",
          "tag": "OW4-U9-V1",
          "lessonStatus": "draft",
          "lessonId": "ow-l4-u9-vocab-1"
        }
      ],
      "tags": [
        "related",
        "vocab-1",
        "force-and-motion",
        "OW4-U9-V1"
      ],
      "additionalExamples": [
        "The ice rink is open every weekend in winter.",
        "We rented skates at the ice rink."
      ],
      "additionalExamplesJp": [
        "そのアイスリンクは冬の間、毎週末開いています。",
        "私たちはアイスリンクでスケート靴を借りました。"
      ]
    },
    {
      "id": "global_twist",
      "type": "related",
      "word": "twist",
      "normalizedWord": "twist",
      "displayEmoji": "🌀↩️",
      "emojiDescription": "a swirl with a curved arrow showing a twisting turn",
      "partOfSpeech": "verb",
      "syllables": "twist",
      "ipa": "twɪst",
      "meaning": "to turn your body or an object around quickly",
      "example": "The skaters twist and spin together on the ice.",
      "exampleJp": "スケーターたちは氷の上で一緒にひねって回転します。",
      "japanese": {
        "word": "ひねる",
        "reading": "ひねる",
        "meaning": "体や物を回すように動かすこと。",
        "needsReview": true
      },
      "sources": [
        {
          "subject": "english",
          "course": "our-world",
          "level": 4,
          "unit": 9,
          "component": "vocab-1",
          "tag": "OW4-U9-V1",
          "lessonStatus": "draft",
          "lessonId": "ow-l4-u9-vocab-1"
        }
      ],
      "tags": [
        "related",
        "vocab-1",
        "force-and-motion",
        "OW4-U9-V1"
      ],
      "additionalExamples": [
        "Twist the cap to open the bottle.",
        "The dancers twist and turn to the music."
      ],
      "additionalExamplesJp": [
        "ボトルを開けるためにキャップをひねってください。",
        "ダンサーたちは音楽に合わせてひねったり回転したりします。"
      ]
    },
    {
      "id": "global_gyroscope",
      "type": "related",
      "word": "gyroscope",
      "normalizedWord": "gyroscope",
      "displayEmoji": "🌐🔄",
      "emojiDescription": "a globe with a circular arrow showing spinning rings",
      "partOfSpeech": "noun",
      "syllables": "gy-ro-scope",
      "ipa": "ˈdʒaɪrəskoʊp",
      "meaning": "a spinning device with rings that can move in many directions",
      "example": "The rider is strapped into the gyroscope and spins in every direction.",
      "exampleJp": "乗る人はジャイロスコープに固定され、あらゆる方向に回転します。",
      "japanese": {
        "word": "ジャイロスコープ",
        "reading": "じゃいろすこーぷ",
        "meaning": "輪の中で回転し、いろいろな方向に動く装置。",
        "needsReview": true
      },
      "sources": [
        {
          "subject": "english",
          "course": "our-world",
          "level": 4,
          "unit": 9,
          "component": "song",
          "tag": "OW4-U9-SG",
          "lessonStatus": "draft",
          "lessonId": "ow-l4-u9-song"
        }
      ],
      "tags": [
        "related",
        "song",
        "force-and-motion",
        "OW4-U9-SG"
      ],
      "additionalExamples": [
        "Astronauts use a gyroscope to train for space.",
        "The gyroscope spins the rider in a circle."
      ],
      "additionalExamplesJp": [
        "宇宙飛行士は宇宙のための訓練にジャイロスコープを使います。",
        "そのジャイロスコープは乗る人を円を描くように回転させます。"
      ]
    },
    {
      "id": "global_independently",
      "type": "related",
      "word": "independently",
      "normalizedWord": "independently",
      "displayEmoji": "🧍‍♂️✔️",
      "emojiDescription": "a standing person with a check mark showing doing something alone",
      "partOfSpeech": "adverb",
      "syllables": "in-de-pen-dent-ly",
      "ipa": "ˌɪndɪˈpɛndəntli",
      "meaning": "without help from anyone or anything else",
      "example": "The rings of the gyroscope move independently of each other.",
      "exampleJp": "ジャイロスコープの輪は、それぞれ独立して動きます。",
      "japanese": {
        "word": "独立して",
        "reading": "どくりつして",
        "meaning": "他のものに頼らず、自分だけで行うこと。",
        "needsReview": true
      },
      "sources": [
        {
          "subject": "english",
          "course": "our-world",
          "level": 4,
          "unit": 9,
          "component": "song",
          "tag": "OW4-U9-SG",
          "lessonStatus": "draft",
          "lessonId": "ow-l4-u9-song"
        }
      ],
      "tags": [
        "related",
        "song",
        "force-and-motion",
        "OW4-U9-SG"
      ],
      "additionalExamples": [
        "Each ring of the gyroscope moves independently.",
        "She finished the project independently, without any help."
      ],
      "additionalExamplesJp": [
        "ジャイロスコープの各輪は独立して動きます。",
        "彼女は誰の助けも借りずに独立してそのプロジェクトを終えました。"
      ]
    },
    {
      "id": "global_motion_sickness",
      "type": "related",
      "word": "motion sickness",
      "normalizedWord": "motion sickness",
      "displayEmoji": "🤢🎢",
      "emojiDescription": "a nauseated face with a roller coaster showing sickness from motion",
      "partOfSpeech": "noun",
      "syllables": "mo-tion sick-ness",
      "ipa": "ˈmoʊʃən ˈsɪknəs",
      "meaning": "a feeling of sickness caused by spinning or moving quickly",
      "example": "The gyroscope doesn't get the rider motion sickness.",
      "exampleJp": "そのジャイロスコープは乗っている人を乗り物酔いにさせません。",
      "japanese": {
        "word": "乗り物酔い",
        "reading": "のりものよい",
        "meaning": "揺れや回転で気分が悪くなること。",
        "needsReview": true
      },
      "sources": [
        {
          "subject": "english",
          "course": "our-world",
          "level": 4,
          "unit": 9,
          "component": "song",
          "tag": "OW4-U9-SG",
          "lessonStatus": "draft",
          "lessonId": "ow-l4-u9-song"
        }
      ],
      "tags": [
        "related",
        "song",
        "force-and-motion",
        "OW4-U9-SG"
      ],
      "additionalExamples": [
        "Some people get motion sickness on long car rides.",
        "Looking out the window can help with motion sickness."
      ],
      "additionalExamplesJp": [
        "長い車の移動で乗り物酔いになる人もいます。",
        "窓の外を見ることは乗り物酔いに役立つことがあります。"
      ]
    },
    {
      "id": "global_structure",
      "type": "related",
      "word": "structure",
      "normalizedWord": "structure",
      "displayEmoji": "🏗️",
      "emojiDescription": "a building crane showing something constructed",
      "partOfSpeech": "noun",
      "syllables": "struc-ture",
      "ipa": "ˈstrʌktʃər",
      "meaning": "something that is built with connected parts",
      "example": "A gyroscope is a structure made of two or three rings.",
      "exampleJp": "ジャイロスコープは、二つか三つの輪でできた構造物です。",
      "japanese": {
        "word": "構造",
        "reading": "こうぞう",
        "meaning": "部品が組み合わさってできているもの。",
        "needsReview": true
      },
      "sources": [
        {
          "subject": "english",
          "course": "our-world",
          "level": 4,
          "unit": 9,
          "component": "song",
          "tag": "OW4-U9-SG",
          "lessonStatus": "draft",
          "lessonId": "ow-l4-u9-song"
        }
      ],
      "tags": [
        "related",
        "song",
        "force-and-motion",
        "OW4-U9-SG"
      ],
      "additionalExamples": [
        "The bridge is a strong structure made of steel.",
        "Every roller coaster has a tall structure to support the track."
      ],
      "additionalExamplesJp": [
        "その橋は鋼鉄でできた頑丈な構造物です。",
        "すべてのジェットコースターにはトラックを支える高い構造物があります。"
      ]
    },
    {
      "id": "global_motion",
      "type": "related",
      "word": "motion",
      "normalizedWord": "motion",
      "displayEmoji": "🏃‍♂️💨",
      "emojiDescription": "a running figure with motion lines",
      "partOfSpeech": "noun",
      "syllables": "mo-tion",
      "ipa": "ˈmoʊʃən",
      "meaning": "the act of moving or changing position",
      "example": "The photo shows the motion of a roller coaster on its track.",
      "exampleJp": "その写真はジェットコースターの軌道上での動きを示しています。",
      "japanese": {
        "word": "動き",
        "reading": "うごき",
        "meaning": "物が位置を変えて動くこと。",
        "needsReview": true
      },
      "sources": [
        {
          "subject": "english",
          "course": "our-world",
          "level": 4,
          "unit": 9,
          "component": "reading",
          "tag": "OW4-U9-RD",
          "lessonStatus": "draft",
          "lessonId": "ow-l4-u9-reading"
        }
      ],
      "tags": [
        "related",
        "reading",
        "roller-coaster",
        "OW4-U9-RD"
      ],
      "additionalExamples": [
        "Slow motion video shows the ball's motion clearly.",
        "The motion of the swing made her feel happy."
      ],
      "additionalExamplesJp": [
        "スローモーションの映像はボールの動きをはっきりと示します。",
        "ブランコの動きは彼女を幸せな気持ちにしました。"
      ]
    },
    {
      "id": "global_theme_park",
      "type": "related",
      "word": "theme park",
      "normalizedWord": "theme park",
      "displayEmoji": "🎢🎡",
      "emojiDescription": "a roller coaster and Ferris wheel showing an amusement park",
      "partOfSpeech": "noun",
      "syllables": "theme park",
      "ipa": "θiːm pɑːrk",
      "meaning": "a large park with rides and games for fun",
      "example": "The roller coaster is at a theme park on the coast of England.",
      "exampleJp": "そのジェットコースターはイングランドの海岸にあるテーマパークにあります。",
      "japanese": {
        "word": "テーマパーク",
        "reading": "てーまぱーく",
        "meaning": "乗り物やゲームがある大きな遊園地。",
        "needsReview": true
      },
      "sources": [
        {
          "subject": "english",
          "course": "our-world",
          "level": 4,
          "unit": 9,
          "component": "reading",
          "tag": "OW4-U9-RD",
          "lessonStatus": "draft",
          "lessonId": "ow-l4-u9-reading"
        }
      ],
      "tags": [
        "related",
        "reading",
        "roller-coaster",
        "OW4-U9-RD"
      ],
      "additionalExamples": [
        "Our class is going on a trip to a theme park.",
        "The theme park has three roller coasters."
      ],
      "additionalExamplesJp": [
        "私たちのクラスはテーマパークへ遠足に行きます。",
        "そのテーマパークには三つのジェットコースターがあります。"
      ]
    },
    {
      "id": "global_describe",
      "type": "academic",
      "word": "describe",
      "normalizedWord": "describe",
      "displayEmoji": "🗣️📝",
      "emojiDescription": "a speaking mouth with a notepad, showing telling and writing what something is like",
      "partOfSpeech": "verb",
      "pos": "verb",
      "ipa": "dɪˈskraɪb",
      "syllables": "de-scribe",
      "meaning": "to say or write what a person, place, or thing is like",
      "example": "Describe the picture in one sentence.",
      "exampleJp": "その絵を一文でdescribeしなさい。",
      "additionalExamples": [
        "Yesterday, we described our favorite sport to the class.",
        "The roller coaster ride has been described in many magazines."
      ],
      "additionalExamplesJp": [
        "昨日、私たちはクラスに好きなスポーツについてdescribeしました。",
        "そのジェットコースターの乗り物は多くの雑誌でdescribeされてきました。"
      ],
      "japanese": {
        "word": "説明する（せつめいする）",
        "reading": "せつめいする",
        "meaning": "人や物、場所がどんなものかを言葉で伝えること。",
        "needsReview": true
      },
      "jp_word": "説明する（せつめいする）",
      "jp_reading": "せつめいする",
      "jp_sentence": "その絵を一文でdescribeしなさい。",
      "jp_meaning": "人や物、場所がどんなものかを言葉で伝えること。",
      "category": "grammar",
      "when_to_use": [
        {
          "context": "test",
          "text": "Use describe when a test asks you to explain what something is like in your own words."
        },
        {
          "context": "school",
          "text": "Use describe when your teacher asks you to tell about a picture, character, or activity in class."
        },
        {
          "context": "real-world",
          "text": "Use describe when you want to help someone picture something they cannot see."
        }
      ],
      "jp_when_to_use": [
        {
          "context": "test",
          "text": "テストで、あるものがどんなものかを自分の言葉で説明するときに使います。"
        },
        {
          "context": "school",
          "text": "授業で、絵や登場人物、活動について先生に説明するときに使います。"
        },
        {
          "context": "real-world",
          "text": "見えないものを相手が想像できるように伝えたいときに使います。"
        }
      ],
      "how_to_use": {
        "structure": "describe + noun (person/place/thing)",
        "patterns": [
          "describe a photo",
          "describe a game",
          "describe what happened",
          "describe the process"
        ]
      },
      "jp_how_to_use": {
        "structure": "describe + noun (person/place/thing)",
        "patterns": [
          "describe a photo",
          "describe a game",
          "describe what happened",
          "describe the process"
        ],
        "needsReview": true
      },
      "examples": [
        {
          "context": "test",
          "en": "Describe the picture in one sentence.",
          "jp": "その絵を一文で説明しなさい。"
        },
        {
          "context": "school",
          "en": "Yesterday, we described our favorite sport to the class.",
          "jp": "昨日、私たちはクラスに好きなスポーツについて説明しました。"
        },
        {
          "context": "real-world",
          "en": "The roller coaster ride has been described in many magazines.",
          "jp": "そのジェットコースターの乗り物は多くの雑誌で説明されてきました。"
        }
      ],
      "collocations": [
        "describe a photo",
        "describe a game",
        "describe the process",
        "briefly describe",
        "describe in detail",
        "describe what happened"
      ],
      "nonExamples": [
        {
          "en": "just point at a photo without saying anything",
          "jp": "何も言わずに写真を指さすだけ。"
        },
        {
          "en": "say only one word about something",
          "jp": "一語だけ言うこと。"
        }
      ],
      "practice_prompt": "Write one sentence that describes your favorite game or activity.",
      "jp_practice_prompt": "自分の好きなゲームや活動について、describeを使って一文書きましょう。",
      "jp_note": "describe は、見たり聞いたりしたことをくわしく言葉で伝えるときに使います。",
      "miniQuiz": [
        {
          "prompt": "Which sentence describes something?",
          "options": [
            "Tetherball is a game with a ball connected to a pole.",
            "Tetherball.",
            "Yes.",
            "Page 155."
          ],
          "correct": 0,
          "explanation": "The first sentence tells what tetherball is like, so it describes it.",
          "jp": "最初の文はテザーボールがどんなものかを伝えているので、describeになります。"
        }
      ],
      "sources": [
        {
          "subject": "english",
          "course": "our-world",
          "level": 4,
          "unit": 9,
          "component": "grammar-1",
          "tag": "OW4-U9-G1",
          "lessonStatus": "draft",
          "lessonId": "ow-l4-u9-grammar-1"
        }
      ],
      "tags": [
        "academic",
        "OW4-AC",
        "grammar-1",
        "description",
        "OW4-U9-G1"
      ]
    },
    {
      "id": "global_match",
      "type": "academic",
      "word": "match",
      "normalizedWord": "match",
      "displayEmoji": "🧩✅",
      "emojiDescription": "a puzzle piece with a check mark showing two things fitting together correctly",
      "partOfSpeech": "verb",
      "pos": "verb",
      "ipa": "mætʃ",
      "syllables": "match",
      "meaning": "to find two things that go together or are the same",
      "example": "Match the picture to the correct sentence.",
      "exampleJp": "絵を正しい文とmatchさせなさい。",
      "additionalExamples": [
        "We matched our vocabulary words with their meanings.",
        "The colors were matched perfectly in the design."
      ],
      "additionalExamplesJp": [
        "私たちは単語をその意味とmatchさせました。",
        "そのデザインでは色が完璧にmatchされていました。"
      ],
      "japanese": {
        "word": "合わせる（あわせる）",
        "reading": "あわせる",
        "meaning": "同じもの、または合うもの同士を見つけること。",
        "needsReview": true
      },
      "jp_word": "合わせる（あわせる）",
      "jp_reading": "あわせる",
      "jp_sentence": "絵を正しい文とmatchさせなさい。",
      "jp_meaning": "同じもの、または合うもの同士を見つけること。",
      "category": "grammar",
      "when_to_use": [
        {
          "context": "test",
          "text": "Use match when a test asks you to connect items that go together, like a word and its meaning."
        },
        {
          "context": "school",
          "text": "Use match when your class plays games or does worksheets that connect related items."
        },
        {
          "context": "real-world",
          "text": "Use match when you compare things outside of school to see if they go together, like clothes or colors."
        }
      ],
      "jp_when_to_use": [
        {
          "context": "test",
          "text": "テストで、単語と意味など関連するものをつなげるときに使います。"
        },
        {
          "context": "school",
          "text": "授業で、関連するものをつなげるゲームやワークシートをするときに使います。"
        },
        {
          "context": "real-world",
          "text": "服の色など、学校の外で物が合うかどうか比べるときに使います。"
        }
      ],
      "how_to_use": {
        "structure": "match + noun (to/with + noun)",
        "patterns": [
          "match the picture",
          "match to the sentence",
          "match with a partner",
          "match the answer"
        ]
      },
      "jp_how_to_use": {
        "structure": "match + noun (to/with + noun)",
        "patterns": [
          "match the picture",
          "match to the sentence",
          "match with a partner",
          "match the answer"
        ],
        "needsReview": true
      },
      "examples": [
        {
          "context": "test",
          "en": "Match the picture to the correct sentence.",
          "jp": "絵を正しい文と合わせなさい。"
        },
        {
          "context": "school",
          "en": "We matched our vocabulary words with their meanings.",
          "jp": "私たちは単語をその意味と合わせました。"
        },
        {
          "context": "real-world",
          "en": "The colors were matched perfectly in the design.",
          "jp": "そのデザインでは色が完璧に合っていました。"
        }
      ],
      "collocations": [
        "match the picture",
        "match the words",
        "match a pair",
        "perfect match",
        "match with a partner",
        "match the answer"
      ],
      "nonExamples": [
        {
          "en": "choose an answer that does not go with the question",
          "jp": "質問に合わない答えを選ぶこと。"
        },
        {
          "en": "guess without comparing anything",
          "jp": "何も比べずに当てずっぽうで答えること。"
        }
      ],
      "practice_prompt": "Match three vocabulary words to their meanings and write the pairs.",
      "jp_practice_prompt": "単語を3つ選び、意味とmatchさせて書きましょう。",
      "jp_note": "match は、二つのものを比べて、同じ、または合うものを見つけるときに使います。",
      "miniQuiz": [
        {
          "prompt": "Which pair is a correct match?",
          "options": [
            "seesaw — a board that goes up and down",
            "seesaw — a ball on a rope",
            "seesaw — a round ride that spins",
            "seesaw — a sport on ice"
          ],
          "correct": 0,
          "explanation": "\"A board that goes up and down\" is the correct meaning for seesaw.",
          "jp": "「上下に動く板」がseesawの正しい意味とmatchします。"
        }
      ],
      "sources": [
        {
          "subject": "english",
          "course": "our-world",
          "level": 4,
          "unit": 9,
          "component": "grammar-1",
          "tag": "OW4-U9-G1",
          "lessonStatus": "draft",
          "lessonId": "ow-l4-u9-grammar-1"
        }
      ],
      "tags": [
        "academic",
        "OW4-AC",
        "grammar-1",
        "matching",
        "OW4-U9-G1"
      ]
    },
    {
      "id": "global_definitions",
      "type": "academic",
      "word": "definitions",
      "normalizedWord": "definitions",
      "displayEmoji": "📖🔎",
      "emojiDescription": "an open book with a magnifying glass showing looking up what a word means",
      "partOfSpeech": "noun",
      "pos": "noun",
      "ipa": "ˌdɛfəˈnɪʃənz",
      "syllables": "def-i-ni-tions",
      "meaning": "sentences that explain what a word means",
      "example": "Which definition matches the word gravity?",
      "exampleJp": "どのdefinitionがgravityという単語に合っていますか。",
      "additionalExamples": [
        "We wrote definitions for the new vocabulary words.",
        "A dictionary gives definitions for thousands of words."
      ],
      "additionalExamplesJp": [
        "私たちは新しい単語のdefinitionsを書きました。",
        "辞書は何千もの単語のdefinitionsを載せています。"
      ],
      "japanese": {
        "word": "定義（ていぎ）",
        "reading": "ていぎ",
        "meaning": "言葉の意味を説明する文。",
        "needsReview": true
      },
      "jp_word": "定義（ていぎ）",
      "jp_reading": "ていぎ",
      "jp_sentence": "どのdefinitionがgravityという単語に合っていますか。",
      "jp_meaning": "言葉の意味を説明する文。",
      "category": "grammar",
      "when_to_use": [
        {
          "context": "test",
          "text": "Use definitions when a test asks you to choose or write what a word means."
        },
        {
          "context": "school",
          "text": "Use definitions when your class studies new vocabulary words and their meanings."
        },
        {
          "context": "real-world",
          "text": "Use definitions when you look up a word you don't know outside of school."
        }
      ],
      "jp_when_to_use": [
        {
          "context": "test",
          "text": "テストで、単語の意味を選んだり書いたりするときに使います。"
        },
        {
          "context": "school",
          "text": "授業で新しい単語とその意味を勉強するときに使います。"
        },
        {
          "context": "real-world",
          "text": "学校の外で知らない単語を調べるときに使います。"
        }
      ],
      "how_to_use": {
        "structure": "This is a/an + noun + which/that + explanation",
        "patterns": [
          "write a definition",
          "give a definition",
          "use which in a definition",
          "clear definitions"
        ]
      },
      "jp_how_to_use": {
        "structure": "This is a/an + noun + which/that + explanation",
        "patterns": [
          "write a definition",
          "give a definition",
          "use which in a definition",
          "clear definitions"
        ],
        "needsReview": true
      },
      "examples": [
        {
          "context": "test",
          "en": "Which definition matches the word gravity?",
          "jp": "どの定義がgravityという単語に合っていますか。"
        },
        {
          "context": "school",
          "en": "We wrote definitions for the new vocabulary words.",
          "jp": "私たちは新しい単語の定義を書きました。"
        },
        {
          "context": "real-world",
          "en": "A dictionary gives definitions for thousands of words.",
          "jp": "辞書は何千もの単語の定義を載せています。"
        }
      ],
      "collocations": [
        "write definitions",
        "clear definitions",
        "give a definition",
        "definitions of new words",
        "short definitions"
      ],
      "nonExamples": [
        {
          "en": "just repeating the word itself",
          "jp": "単語をそのまま繰り返すだけ。"
        },
        {
          "en": "an example sentence with no explanation",
          "jp": "説明のない例文だけ。"
        }
      ],
      "practice_prompt": "Write definitions for two new words from this unit.",
      "jp_practice_prompt": "このユニットの新しい単語を2つ選び、definitionsを書きましょう。",
      "jp_note": "definitions は、言葉の意味を他の人に分かるように説明する文です。",
      "miniQuiz": [
        {
          "prompt": "Which sentence is a definition?",
          "options": [
            "A seesaw is a board that goes up and down when people sit on it.",
            "I like the seesaw.",
            "Seesaw!",
            "Look at the seesaw."
          ],
          "correct": 0,
          "explanation": "The first sentence explains what a seesaw is, so it is a definition.",
          "jp": "最初の文はseesawが何かを説明しているので、definitionです。"
        }
      ],
      "sources": [
        {
          "subject": "english",
          "course": "our-world",
          "level": 4,
          "unit": 9,
          "component": "grammar-2",
          "tag": "OW4-U9-G2",
          "lessonStatus": "draft",
          "lessonId": "ow-l4-u9-grammar-2"
        }
      ],
      "tags": [
        "academic",
        "OW4-AC",
        "grammar-2",
        "explanation",
        "OW4-U9-G2"
      ]
    },
    {
      "id": "global_instructions",
      "type": "academic",
      "word": "instructions",
      "normalizedWord": "instructions",
      "displayEmoji": "📋➡️",
      "emojiDescription": "a clipboard with an arrow showing step-by-step directions to follow",
      "partOfSpeech": "noun",
      "pos": "noun",
      "ipa": "ɪnˈstrʌkʃənz",
      "syllables": "in-struc-tions",
      "meaning": "steps that tell you how to do something",
      "example": "Read the instructions before you answer the questions.",
      "exampleJp": "質問に答える前にinstructionsを読みなさい。",
      "additionalExamples": [
        "The teacher gave instructions for making a thaumatrope.",
        "The instructions explain how to build the project step by step."
      ],
      "additionalExamplesJp": [
        "先生はthaumatropeの作り方についてinstructionsを出しました。",
        "そのinstructionsはプロジェクトの作り方を段階的に説明しています。"
      ],
      "japanese": {
        "word": "説明書（せつめいしょ）",
        "reading": "せつめいしょ",
        "meaning": "何かのやり方を伝える手順。",
        "needsReview": true
      },
      "jp_word": "説明書（せつめいしょ）",
      "jp_reading": "せつめいしょ",
      "jp_sentence": "質問に答える前にinstructionsを読みなさい。",
      "jp_meaning": "何かのやり方を伝える手順。",
      "category": "grammar",
      "when_to_use": [
        {
          "context": "test",
          "text": "Use instructions when a test tells you the steps to follow before you answer."
        },
        {
          "context": "school",
          "text": "Use instructions when your teacher explains the steps for an activity or project."
        },
        {
          "context": "real-world",
          "text": "Use instructions when you build or make something and need to follow the steps in order."
        }
      ],
      "jp_when_to_use": [
        {
          "context": "test",
          "text": "テストで、答える前に従うべき手順が示されているときに使います。"
        },
        {
          "context": "school",
          "text": "先生が活動やプロジェクトの手順を説明するときに使います。"
        },
        {
          "context": "real-world",
          "text": "何かを作るときに、順番通りに手順に従う必要があるときに使います。"
        }
      ],
      "how_to_use": {
        "structure": "follow/read/give + instructions",
        "patterns": [
          "follow the instructions",
          "read the instructions",
          "give instructions",
          "step-by-step instructions"
        ]
      },
      "jp_how_to_use": {
        "structure": "follow/read/give + instructions",
        "patterns": [
          "follow the instructions",
          "read the instructions",
          "give instructions",
          "step-by-step instructions"
        ],
        "needsReview": true
      },
      "examples": [
        {
          "context": "test",
          "en": "Read the instructions before you answer the questions.",
          "jp": "質問に答える前に説明を読みなさい。"
        },
        {
          "context": "school",
          "en": "The teacher gave instructions for making a thaumatrope.",
          "jp": "先生はthaumatropeの作り方について説明をしました。"
        },
        {
          "context": "real-world",
          "en": "The instructions explain how to build the project step by step.",
          "jp": "その説明書はプロジェクトの作り方を段階的に説明しています。"
        }
      ],
      "collocations": [
        "follow instructions",
        "give instructions",
        "read instructions",
        "clear instructions",
        "step-by-step instructions"
      ],
      "nonExamples": [
        {
          "en": "a single word with no steps",
          "jp": "手順のない一語だけ。"
        },
        {
          "en": "an opinion about the activity",
          "jp": "その活動についての意見だけ。"
        }
      ],
      "practice_prompt": "Write three instructions for playing your favorite game.",
      "jp_practice_prompt": "好きなゲームの遊び方について、instructionsを3つ書きましょう。",
      "jp_note": "instructions は、何かをするための順番通りの説明です。",
      "miniQuiz": [
        {
          "prompt": "Which sentence is an instruction?",
          "options": [
            "Cut out two circles of cardstock paper.",
            "I like thaumatropes.",
            "The thaumatrope is fun.",
            "That was a good project."
          ],
          "correct": 0,
          "explanation": "The first sentence tells you a step to follow, so it is an instruction.",
          "jp": "最初の文は従うべき手順を伝えているので、instructionです。"
        }
      ],
      "sources": [
        {
          "subject": "english",
          "course": "our-world",
          "level": 4,
          "unit": 9,
          "component": "grammar-2",
          "tag": "OW4-U9-G2",
          "lessonStatus": "draft",
          "lessonId": "ow-l4-u9-grammar-2"
        }
      ],
      "tags": [
        "academic",
        "OW4-AC",
        "grammar-2",
        "explanation",
        "OW4-U9-G2"
      ]
    },
    {
      "id": "global_description",
      "type": "academic",
      "word": "description",
      "normalizedWord": "description",
      "displayEmoji": "📋",
      "emoji": "📋",
      "emojiDescription": "academic study icon",
      "ipa": "dɪˈskrɪpʃən",
      "syllables": "de-scrip-tion",
      "partOfSpeech": "noun",
      "pos": "noun",
      "sample": "Write a description of your hobby.",
      "example": "Write a description of your hobby.",
      "jp_word": "説明（せつめい）",
      "jp_reading": "せつめい",
      "jp_sentence": "自分の趣味の説明（せつめい）を書きます。",
      "jp_tags": [
        "needs-review"
      ],
      "category": "writing",
      "meaning": "words that tell what something is like",
      "jp_meaning": "物や人、考えがどんなものかを言葉で伝えることです。",
      "when_to_use": [
        {
          "context": "test",
          "text": "Use description when a test asks you to recognize or use this school idea correctly."
        },
        {
          "context": "school",
          "text": "Use description when your class talks about writing work."
        },
        {
          "context": "real-world",
          "text": "Use description when you explain the idea clearly outside the textbook."
        }
      ],
      "jp_when_to_use": [
        {
          "context": "test",
          "text": "テストで、ものの様子を伝える文を選ぶときに使います。"
        },
        {
          "context": "school",
          "text": "学校で、趣味や写真、人物について書くときに使います。"
        },
        {
          "context": "real-world",
          "text": "友だちに何かがどんなものか伝えるときに使います。"
        }
      ],
      "how_to_use": {
        "structure": "describe + details",
        "patterns": [
          "write a description",
          "give a description",
          "description of a hobby",
          "short description"
        ]
      },
      "jp_how_to_use": {
        "structure": "describe + details",
        "patterns": [
          "write a description",
          "give a description",
          "description of a hobby",
          "short description"
        ],
        "needsReview": true
      },
      "examples": [
        {
          "context": "test",
          "en": "Which answer shows the description?",
          "jp": "description = どんなものかの説明"
        },
        {
          "context": "school",
          "en": "Write a description of your hobby.",
          "jp": "趣味の説明"
        },
        {
          "context": "real-world",
          "en": "Use description to explain your thinking clearly.",
          "jp": "様子を伝える"
        }
      ],
      "collocations": [
        "write a description",
        "give a description",
        "short description",
        "clear description",
        "description of a hobby"
      ],
      "nonExamples": [
        {
          "en": "a name only",
          "jp": "名前だけで、どんなものか説明していません。"
        },
        {
          "en": "yes or no",
          "jp": "答えだけで説明ではありません。"
        },
        {
          "en": "a number with no detail",
          "jp": "数字だけで詳しくありません。"
        }
      ],
      "practice_prompt": "Write one Unit 8 sentence that uses description correctly.",
      "jp_practice_prompt": "自分の hobby について、どんなものかを two details で説明しましょう。",
      "jp_note": "description は、相手が頭の中でイメージできるように、特徴や様子を伝える文です。",
      "miniQuiz": [
        {
          "prompt": "Which one is a description?",
          "options": [
            "Geocaching is an outdoor hobby with clues and a compass.",
            "Geocaching.",
            "Yes.",
            "Page 140."
          ],
          "correct": 0,
          "explanation": "The first sentence tells what geocaching is like.",
          "jp": "この文は geocaching がどんな hobby かを伝えているので、description です。"
        }
      ],
      "japanese": {
        "word": "説明（せつめい）",
        "reading": "せつめい",
        "meaning": "物や人、考えがどんなものかを言葉で伝えることです。",
        "needsReview": true
      },
      "sources": [
        {
          "subject": "english",
          "course": "our-world",
          "level": 4,
          "unit": 8,
          "component": "writing",
          "lessonId": "ow-l4-u8-writing",
          "tag": "OW4-U8-WR",
          "lessonStatus": "draft"
        },
        {
          "subject": "english",
          "course": "our-world",
          "level": 4,
          "unit": 9,
          "component": "writing",
          "tag": "OW4-U9-WR",
          "lessonStatus": "draft",
          "lessonId": "ow-l4-u9-writing"
        }
      ],
      "tags": [
        "academic",
        "OW4-AC",
        "writing",
        "explanation",
        "OW4-U8-WR",
        "OW4-U9-WR"
      ],
      "additionalExamples": [
        "The book gives a long description of the castle.",
        "Write a description of your best friend."
      ],
      "exampleJp": "あなたの趣味の説明を書きなさい。",
      "additionalExamplesJp": [
        "その本はその城について長い説明をしています。",
        "あなたの親友についての説明を書きなさい。"
      ]
    }
  ]
}
